jupyterlab_quick_share/__init__.py
jupyterlab_quick_share/_version.py
jupyterlab_quick_share/handlers.py
jupyterlab_quick_share/tests/__init__.py
jupyterlab_quick_share/tests/test_handlers.py
jupyterlab_quick_share-0.1.7.data/data/etc/jupyter/jupyter_server_config.d/jupyterlab_quick_share.json
jupyterlab_quick_share-0.1.7.data/data/share/jupyter/labextensions/jupyterlab-quick-share/package.json
jupyterlab_quick_share-0.1.7.data/data/share/jupyter/labextensions/jupyterlab-quick-share/schemas/jupyterlab-quick-share/package.json.orig
jupyterlab_quick_share-0.1.7.data/data/share/jupyter/labextensions/jupyterlab-quick-share/schemas/jupyterlab-quick-share/plugin.json
jupyterlab_quick_share-0.1.7.data/data/share/jupyter/labextensions/jupyterlab-quick-share/static/675.d52c938f18826207b568.js
jupyterlab_quick_share-0.1.7.data/data/share/jupyter/labextensions/jupyterlab-quick-share/static/728.49c96ad5b58d0d0eb59d.js
jupyterlab_quick_share-0.1.7.data/data/share/jupyter/labextensions/jupyterlab-quick-share/static/remoteEntry.b5cf2e4acca24ecc627d.js
jupyterlab_quick_share-0.1.7.data/data/share/jupyter/labextensions/jupyterlab-quick-share/static/style.js
jupyterlab_quick_share-0.1.7.data/data/share/jupyter/labextensions/jupyterlab-quick-share/static/third-party-licenses.json
jupyterlab_quick_share-0.1.7.data/data/share/jupyter/labextensions/jupyterlab-quick-share/install.json
jupyterlab_quick_share-0.1.7.dist-info/METADATA
jupyterlab_quick_share-0.1.7.dist-info/WHEEL
jupyterlab_quick_share-0.1.7.dist-info/licenses/LICENSE
jupyterlab_quick_share-0.1.7.dist-info/RECORD
